hclib/__init__.py
hclib/__main__.py
hclib/cli.py
hclib/config.py
hclib/context.py
hclib/judge.py
hclib/utils.py
hashcode_bot-0.8.2.dist-info/METADATA
hashcode_bot-0.8.2.dist-info/WHEEL
hashcode_bot-0.8.2.dist-info/entry_points.txt
hashcode_bot-0.8.2.dist-info/top_level.txt
hashcode_bot-0.8.2.dist-info/RECORD
